manage_json/__init__.py
manage_json/manage_json.py
manage_json-1.0.7.dist-info/licenses/LICENSE
manage_json-1.0.7.dist-info/METADATA
manage_json-1.0.7.dist-info/WHEEL
manage_json-1.0.7.dist-info/top_level.txt
manage_json-1.0.7.dist-info/RECORD
