Metadata-Version: 2.4
Name: manage_json
Version: 1.0.7
Author: geko1
License:                     GNU GENERAL PUBLIC LICENSE
Project-URL: Repository, https://github.com/unixtux/manage_json
Requires-Python: >=3.8
License-File: LICENSE
Requires-Dist: apitele
Dynamic: license-file
